authentication/__init__.py
authentication/auth.py
authentication/errors.py
authentication/models.py
authentication/routes.py
authentication/schemes.py
authentication/settings.py
authentication/utils.py
connectkit_fastapiauthentication-1.6.0.dist-info/METADATA
connectkit_fastapiauthentication-1.6.0.dist-info/WHEEL
connectkit_fastapiauthentication-1.6.0.dist-info/licenses/LICENSE
connectkit_fastapiauthentication-1.6.0.dist-info/RECORD
