Metadata-Version: 2.1
Name: ConnectKit-FastAPIAuthentication
Version: 1.6.0
Summary: User JWT Authentication for FastAPI services
Keywords: connectkit,authentication,jwt,cookie,otp,totp,fastapi
Author-Email: RealMetamorph <andr.timchuk@yandex.ru>
License: The MIT License (MIT)
Classifier: Development Status :: 5 - Production/Stable
Classifier: Programming Language :: Python :: 3
Classifier: Intended Audience :: Developers
Classifier: Framework :: FastAPI
Classifier: License :: OSI Approved :: MIT License
Project-URL: Homepage, https://github.com/mtuciru/ConnectKit-FastAPIAuthentication
Project-URL: Repository, https://github.com/mtuciru/ConnectKit-FastAPIAuthentication.git
Requires-Python: >=3.9
Requires-Dist: pydantic>=2.5.3
Requires-Dist: pydantic-settings>=2.1.0
Requires-Dist: fastapi>=0.110.0
Requires-Dist: PyJWT>=2.8.0
Requires-Dist: argon2-cffi>=23.1.0
Requires-Dist: pyotp>=2.9.0
Requires-Dist: ConnectKit-Database[asyncpg]>=1.3.2
Requires-Dist: ietfparse>=1.9.0
